particlespy/__init__.py
particlespy/api.py
particlespy/custom_kernels.py
particlespy/find_zoneaxis.py
particlespy/particle_analysis.py
particlespy/particle_load.py
particlespy/particle_save.py
particlespy/ptcl_class.py
particlespy/radial_profile.py
particlespy/seg_ui.py
particlespy/segimgs.py
particlespy/segptcls.py
particlespy/parameters/manual_mask.npy
particlespy/parameters/parameters_current.hdf5
particlespy/parameters/parameters_previous.hdf5
particlespy/tests/__init__.py
particlespy/tests/generate_test_data.py
particlespy/tests/test_particle_analysis.py
particlespy/tests/test_particle_clustering.py
particlespy/tests/test_particle_io.py
particlespy/tests/test_plotting.py
particlespy-0.6.3.dist-info/licenses/LICENSE
particlespy-0.6.3.dist-info/METADATA
particlespy-0.6.3.dist-info/WHEEL
particlespy-0.6.3.dist-info/top_level.txt
particlespy-0.6.3.dist-info/RECORD
