Metadata-Version: 2.4
Name: particlespy
Version: 0.6.3
Summary: A package to perform particle segmentation and analysis
Home-page: https://github.com/ePSIC-DLS/particlespy
Author: Thomas Slater
Author-email: tjaslater@gmail.com
Classifier: Programming Language :: Python :: 3
Classifier: License :: OSI Approved :: GNU General Public License v3 (GPLv3)
Classifier: Operating System :: OS Independent
License-File: LICENSE
Requires-Dist: hyperspy>=1.7
Requires-Dist: scikit-image>=0.17.1
Requires-Dist: scikit-learn>=0.21
Requires-Dist: trackpy
Requires-Dist: numpy>=1.16.5
Requires-Dist: PyQt5<6.0,>=5.14.0
Dynamic: author
Dynamic: author-email
Dynamic: classifier
Dynamic: description
Dynamic: description-content-type
Dynamic: home-page
Dynamic: license-file
Dynamic: requires-dist
Dynamic: summary
